{
  "project_info": {
    "project_number": "529394527666",
    "firebase_url": "https://mdm-cyclopes.firebaseio.com",
    "project_id": "mdm-cyclopes",
    "storage_bucket": "mdm-cyclopes.appspot.com"
  },
  "client": [
    {
      "client_info": {
        "mobilesdk_app_id": "1:529394527666:android:6091b6a98e5adb7c",
        "android_client_info": {
          "package_name": "com.mdmobile.cyclopes"
        }
      },
      "oauth_client": [
        {
          "client_id": "529394527666-1jk9636esm5q18oec1fp3b41v1mcrgec.apps.googleusercontent.com",
          "client_type": 3
        }
      ],
      "api_key": [
        {
          "current_key": "AIzaSyAXXPIQTz4F70vrmoDNNPWNMb0X2vbiO84"
        }
      ],
      "services": {
        "analytics_service": {
          "status": 1
        },
        "appinvite_service": {
          "status": 1,
          "other_platform_oauth_client": []
        },
        "ads_service": {
          "status": 2
        }
      }
    }
  ],
  "configuration_version": "1"
}